<?xml version="1.0" encoding="UTF-8"?>
<jasperPrint xmlns="http://jasperreports.sourceforge.net/jasperreports/print" xmlns:xsi="http://www.w3.org/2001/XMLSchema-instance" xsi:schemaLocation="http://jasperreports.sourceforge.net/jasperreports/print http://jasperreports.sourceforge.net/xsd/jasperprint.xsd" name="report name" pageWidth="595" pageHeight="842" topMargin="20" leftMargin="20" bottomMargin="20" rightMargin="20" locale="en_IN" timezone="Asia/Calcutta">
	<property name="net.sf.jasperreports.export.xml.start.page.index" value="0"/>
	<property name="net.sf.jasperreports.export.xml.end.page.index" value="0"/>
	<property name="net.sf.jasperreports.export.xml.page.count" value="1"/>
	<origin band="background"/>
	<origin band="title"/>
	<origin band="columnHeader"/>
	<origin band="detail"/>
	<origin band="pageFooter"/>
	<page>
		<text textHeight="12.578125" lineSpacingFactor="1.2578125" leadingOffset="-2.524414">
			<reportElement x="231" y="31" width="106" height="20" origin="1" srcId="1"/>
			<textContent><![CDATA[Employee Report]]></textContent>
		</text>
		<text textHeight="12.578125" lineSpacingFactor="1.2578125" leadingOffset="-2.524414">
			<reportElement x="103" y="68" width="100" height="20" origin="2" srcId="2"/>
			<textContent><![CDATA[Employee Id]]></textContent>
		</text>
		<text textHeight="12.578125" lineSpacingFactor="1.2578125" leadingOffset="-2.524414">
			<reportElement x="203" y="68" width="100" height="20" origin="2" srcId="3"/>
			<textContent><![CDATA[Employee Name]]></textContent>
		</text>
		<text textHeight="12.578125" lineSpacingFactor="1.2578125" leadingOffset="-2.524414">
			<reportElement x="303" y="68" width="100" height="20" origin="2" srcId="4"/>
			<textContent><![CDATA[Employee Salary]]></textContent>
		</text>
		<text textHeight="12.578125" lineSpacingFactor="1.2578125" leadingOffset="-2.524414" valueClass="java.lang.Integer">
			<reportElement x="103" y="89" width="100" height="20" origin="3" srcId="5"/>
			<textContent><![CDATA[111]]></textContent>
		</text>
		<text textHeight="12.578125" lineSpacingFactor="1.2578125" leadingOffset="-2.524414">
			<reportElement x="203" y="89" width="100" height="20" origin="3" srcId="6"/>
			<textContent><![CDATA[aaa]]></textContent>
		</text>
		<text textHeight="12.578125" lineSpacingFactor="1.2578125" leadingOffset="-2.524414" valueClass="java.lang.Double">
			<reportElement x="303" y="89" width="100" height="20" origin="3" srcId="7"/>
			<textContent><![CDATA[100.0]]></textContent>
		</text>
		<text textHeight="12.578125" lineSpacingFactor="1.2578125" leadingOffset="-2.524414" valueClass="java.lang.Integer">
			<reportElement x="103" y="110" width="100" height="20" origin="3" srcId="5"/>
			<textContent><![CDATA[222]]></textContent>
		</text>
		<text textHeight="12.578125" lineSpacingFactor="1.2578125" leadingOffset="-2.524414">
			<reportElement x="203" y="110" width="100" height="20" origin="3" srcId="6"/>
			<textContent><![CDATA[bbb]]></textContent>
		</text>
		<text textHeight="12.578125" lineSpacingFactor="1.2578125" leadingOffset="-2.524414" valueClass="java.lang.Double">
			<reportElement x="303" y="110" width="100" height="20" origin="3" srcId="7"/>
			<textContent><![CDATA[200.0]]></textContent>
		</text>
		<text textHeight="12.578125" lineSpacingFactor="1.2578125" leadingOffset="-2.524414" valueClass="java.lang.Integer">
			<reportElement x="103" y="131" width="100" height="20" origin="3" srcId="5"/>
			<textContent><![CDATA[333]]></textContent>
		</text>
		<text textHeight="12.578125" lineSpacingFactor="1.2578125" leadingOffset="-2.524414">
			<reportElement x="203" y="131" width="100" height="20" origin="3" srcId="6"/>
			<textContent><![CDATA[ccc]]></textContent>
		</text>
		<text textHeight="12.578125" lineSpacingFactor="1.2578125" leadingOffset="-2.524414" valueClass="java.lang.Double">
			<reportElement x="303" y="131" width="100" height="20" origin="3" srcId="7"/>
			<textContent><![CDATA[300.0]]></textContent>
		</text>
		<text textHeight="12.578125" lineSpacingFactor="1.2578125" leadingOffset="-2.524414" valueClass="java.lang.Integer">
			<reportElement x="103" y="152" width="100" height="20" origin="3" srcId="5"/>
			<textContent><![CDATA[444]]></textContent>
		</text>
		<text textHeight="12.578125" lineSpacingFactor="1.2578125" leadingOffset="-2.524414">
			<reportElement x="203" y="152" width="100" height="20" origin="3" srcId="6"/>
			<textContent><![CDATA[ddd]]></textContent>
		</text>
		<text textHeight="12.578125" lineSpacingFactor="1.2578125" leadingOffset="-2.524414" valueClass="java.lang.Double">
			<reportElement x="303" y="152" width="100" height="20" origin="3" srcId="7"/>
			<textContent><![CDATA[400.0]]></textContent>
		</text>
		<text textHeight="12.578125" lineSpacingFactor="1.2578125" leadingOffset="-2.524414" valueClass="java.lang.Integer">
			<reportElement x="103" y="173" width="100" height="20" origin="3" srcId="5"/>
			<textContent><![CDATA[555]]></textContent>
		</text>
		<text textHeight="12.578125" lineSpacingFactor="1.2578125" leadingOffset="-2.524414">
			<reportElement x="203" y="173" width="100" height="20" origin="3" srcId="6"/>
			<textContent><![CDATA[eee]]></textContent>
		</text>
		<text textHeight="12.578125" lineSpacingFactor="1.2578125" leadingOffset="-2.524414" valueClass="java.lang.Double">
			<reportElement x="303" y="173" width="100" height="20" origin="3" srcId="7"/>
			<textContent><![CDATA[500.0]]></textContent>
		</text>
		<text textAlignment="Right" textHeight="12.578125" lineSpacingFactor="1.2578125" leadingOffset="-2.524414">
			<reportElement x="372" y="797" width="80" height="20" origin="4" srcId="8"/>
			<textContent><![CDATA[Page 1 of]]></textContent>
		</text>
		<text textHeight="12.578125" lineSpacingFactor="1.2578125" leadingOffset="-2.524414">
			<reportElement x="452" y="797" width="40" height="20" origin="4" srcId="9"/>
			<textContent><![CDATA[ 1]]></textContent>
		</text>
		<text textHeight="12.578125" lineSpacingFactor="1.2578125" leadingOffset="-2.1972656" valueClass="java.util.Date" pattern="EEEEE dd MMMMM yyyy">
			<reportElement x="74" y="797" width="100" height="20" origin="4" srcId="10"/>
			<textContent><![CDATA[Monday 24 March ]]></textContent>
		</text>
	</page>
</jasperPrint>
